abc_xml_converter/__init__.py
abc_xml_converter/abc2xml.py
abc_xml_converter/pyparsing.py
abc_xml_converter/xml2abc.py
abc_xml_converter-1.0.1.dist-info/LICENSE
abc_xml_converter-1.0.1.dist-info/METADATA
abc_xml_converter-1.0.1.dist-info/WHEEL
abc_xml_converter-1.0.1.dist-info/top_level.txt
abc_xml_converter-1.0.1.dist-info/RECORD
