Metadata-Version: 2.1
Name: abc_xml_converter
Version: 1.0.1
Summary: ABC-XML Converter
Home-page: https://github.com/sebastian-eck/abc_xml_converter
Author: Sebastian Oliver Eck
License: GNU Lesser General Public License
Classifier: Programming Language :: Python :: 3
Classifier: Programming Language :: Python :: 3.8
Classifier: Programming Language :: Python :: 3.9
Classifier: Programming Language :: Python :: 3.10
Classifier: License :: OSI Approved :: GNU Lesser General Public License v3 (LGPLv3)
Classifier: Operating System :: Microsoft :: Windows
Classifier: Operating System :: Unix
Classifier: Development Status :: 4 - Beta
Classifier: Intended Audience :: Science/Research
Classifier: Natural Language :: English
License-File: LICENSE
Requires-Dist: setuptools ~=69.5.1
Requires-Dist: pyparsing ~=3.1.1
